diabolocom_api_client/__init__.py
diabolocom_api_client/client.py
diabolocom_api_client/resources/__init__.py
diabolocom_api_client/resources/base.py
diabolocom_api_client/resources/campaigns.py
diabolocom_api_client/utils.py
diabolocom_api_client-0.1.3.dist-info/WHEEL
diabolocom_api_client-0.1.3.dist-info/METADATA
diabolocom_api_client-0.1.3.dist-info/RECORD
